LICENSE
MANIFEST.in
README
setup.py
django_wordpress.egg-info/PKG-INFO
django_wordpress.egg-info/SOURCES.txt
django_wordpress.egg-info/dependency_links.txt
django_wordpress.egg-info/not-zip-safe
django_wordpress.egg-info/top_level.txt
wp/__init__.py
wp/admin.py
wp/models.py
wp/tests.py
wp/views.py
wp/templates/wp/recent_comments.html
wp/templates/wp/recent_posts.html
wp/templatetags/__init__.py
wp/templatetags/wordpress_tags.py